{"quote":{"language":"en-US","region":"US","quoteType":"CRYPTOCURRENCY","quoteSourceName":"CoinMarketCap","triggerable":true,"currency":"USD","exchange":"CCC","shortName":"Bitcoin USD","exchangeTimezoneName":"Europe\/London","exchangeTimezoneShortName":"GMT","gmtOffSetMilliseconds":0,"market":"ccc_market","esgPopulated":false,"marketState":"REGULAR","regularMarketChange":1519.168,"regularMarketChangePercent":3.2111356,"regularMarketTime":1614684182,"regularMarketPrice":48828.473,"regularMarketDayHigh":50076.68,"regularMarketDayRange":"48461.793 - 50076.68","regularMarketDayLow":48461.793,"regularMarketVolume":49987129344,"regularMarketPreviousClose":48823.957,"fullExchangeName":"CCC","regularMarketOpen":48823.957,"averageDailyVolume3Month":62760487911,"fiftyTwoWeekLowChange":44721.492,"fiftyTwoWeekLowChangePercent":10.88914,"fiftyTwoWeekRange":"4106.981 - 58330.57","fiftyTwoWeekHighChange":-9502.098,"fiftyTwoWeekHighChangePercent":-0.16290082,"fiftyTwoWeekLow":4106.981,"fiftyTwoWeekHigh":58330.57,"sourceInterval":15,"exchangeDataDelayedBy":0,"firstTradeDateMilliseconds":1410908400000,"priceHint":2,"tradeable":false,"symbol":"BTC-USD"},"virtual":{"symbol":"BTC-USD","name":"Bitcoin USD","lastUpdated":1614684301}}