{"quote":{"language":"en-US","region":"US","quoteType":"MUTUALFUND","quoteSourceName":"Delayed Quote","triggerable":false,"marketState":"CLOSED","regularMarketTime":1561759658,"fullExchangeName":"YHD","sourceInterval":15,"exchangeDataDelayedBy":0,"exchange":"YHD","exchangeTimezoneName":"America\/New_York","exchangeTimezoneShortName":"EST","gmtOffSetMilliseconds":-18000000,"market":"us_market","esgPopulated":false,"tradeable":false,"priceHint":2,"symbol":"BTC"},"virtual":{"symbol":"BTC","name":"BTC","lastUpdated":1608881843}}